bode_django_error_pages-0.0.2.dist-info/DESCRIPTION.rst
bode_django_error_pages-0.0.2.dist-info/METADATA
bode_django_error_pages-0.0.2.dist-info/RECORD
bode_django_error_pages-0.0.2.dist-info/WHEEL
bode_django_error_pages-0.0.2.dist-info/metadata.json
bode_django_error_pages-0.0.2.dist-info/top_level.txt
bode_error_pages/__init__.py
bode_error_pages/admin.py
bode_error_pages/apps.py
bode_error_pages/models.py
bode_error_pages/tests.py
bode_error_pages/views.py
bode_error_pages/migrations/__init__.py
bode_error_pages/templates/errors/403.html
bode_error_pages/templates/errors/404.html
bode_error_pages/templates/errors/500.html
