Metadata-Version: 2.0
Name: bode-django-error-pages
Version: 0.0.2
Summary: This is a simple project to handle http errors responses to Bode Django Projects
Home-page: https://github.com/bodedev/django-error-pages
Author: Bode.io Dev Team
Author-email: devs@bode.io
License: MIT
Keywords: django error pages
Platform: UNKNOWN
Classifier: Development Status :: 1 - Planning
Classifier: Intended Audience :: Developers
Classifier: Topic :: Internet :: WWW/HTTP
Classifier: License :: OSI Approved :: MIT License
Classifier: Programming Language :: Python :: 2
Classifier: Programming Language :: Python :: 2.7
Classifier: Programming Language :: Python :: 3
Classifier: Programming Language :: Python :: 3.3
Classifier: Programming Language :: Python :: 3.4
Classifier: Programming Language :: Python :: 3.5
Requires-Dist: django
Provides-Extra: dev
Requires-Dist: check-manifest; extra == 'dev'
Provides-Extra: test
Requires-Dist: coverage; extra == 'test'
